crest/resource.py
crest/__init__.py
Python_Crest-0.1.6.dist-info/metadata.json
Python_Crest-0.1.6.dist-info/top_level.txt
Python_Crest-0.1.6.dist-info/RECORD
Python_Crest-0.1.6.dist-info/WHEEL
Python_Crest-0.1.6.dist-info/DESCRIPTION.rst
Python_Crest-0.1.6.dist-info/METADATA
