Metadata-Version: 2.0
Name: Python-Crest
Version: 0.1.6
Summary: A simple REST client for Python.
Home-page: https://github.com/RussellLuo/crest
Author: RussellLuo
Author-email: luopeng.he@gmail.com
License: MIT
Keywords: REST,Python
Platform: UNKNOWN
Requires-Dist: requests (>=2.5.0)
